hyperdb/__init__.py
hyperdb/galaxy_brain_math_shit.py
hyperdb/hyperdb.py
tests/__init__.py
tests/test_galaxy_brain_math_shit.py
hyperdb_python-0.1.3.dist-info/LICENSE
hyperdb_python-0.1.3.dist-info/METADATA
hyperdb_python-0.1.3.dist-info/WHEEL
hyperdb_python-0.1.3.dist-info/top_level.txt
hyperdb_python-0.1.3.dist-info/RECORD
