Metadata-Version: 2.1
Name: hyperdb-python
Version: 0.1.3
Summary: A hyper-fast local vector database for use with LLM Agents.
Home-page: https://github.com/jdagdelen/hyperdb
Author: John Dagdelen
Author-email: jjdagdelen@gmail.com
Classifier: Development Status :: 3 - Alpha
Classifier: Intended Audience :: Developers
Classifier: License :: OSI Approved :: MIT License
Classifier: Programming Language :: Python :: 3
Classifier: Programming Language :: Python :: 3.8
Classifier: Programming Language :: Python :: 3.9
Classifier: Programming Language :: Python :: 3.10
Requires-Python: >=3.8
License-File: LICENSE
Requires-Dist: numpy
Requires-Dist: openai
